unifetch/__init__.py
unifetch/__main__.py
unifetch/universities.json
unifetch/ASCII_generator/__init__.py
unifetch/ASCII_generator/img2img_color.py
unifetch/ASCII_generator/utils.py
unifetch/ASCII_generator/fonts/DejaVu Fonts License.txt
unifetch/ASCII_generator/fonts/DejaVuSansMono-Bold.ttf
unifetch/ASCII_generator/fonts/DejaVuSansMono-BoldOblique.ttf
unifetch/ASCII_generator/fonts/DejaVuSansMono-Oblique.ttf
unifetch/ASCII_generator/fonts/DejaVuSansMono.ttf
unifetch/ASCII_generator/fonts/arial-unicode.ttf
unifetch/ASCII_generator/fonts/simsun.ttc
unifetch/crests/abdn.png
unifetch/crests/bath.png
unifetch/crests/bham.png
unifetch/crests/bris.png
unifetch/crests/cam.png
unifetch/crests/cf.png
unifetch/crests/cov.png
unifetch/crests/dmu.png
unifetch/crests/dundee.png
unifetch/crests/dur.png
unifetch/crests/ed.png
unifetch/crests/essex.png
unifetch/crests/ex.png
unifetch/crests/gla.png
unifetch/crests/harper-adams.png
unifetch/crests/hw.png
unifetch/crests/ic.png
unifetch/crests/kcl.png
unifetch/crests/lancs.png
unifetch/crests/lboro.png
unifetch/crests/le.png
unifetch/crests/leeds.png
unifetch/crests/liv.png
unifetch/crests/lse.png
unifetch/crests/man.png
unifetch/crests/mmu.png
unifetch/crests/ncl.png
unifetch/crests/northumbria.png
unifetch/crests/nott.png
unifetch/crests/ntu.png
unifetch/crests/ox.png
unifetch/crests/port.png
unifetch/crests/qmw.png
unifetch/crests/qub.png
unifetch/crests/rdg.png
unifetch/crests/rhul.png
unifetch/crests/shef.png
unifetch/crests/shu.png
unifetch/crests/soton.png
unifetch/crests/st-and.png
unifetch/crests/stir.png
unifetch/crests/strath.png
unifetch/crests/sund.png
unifetch/crests/surrey.png
unifetch/crests/susx.png
unifetch/crests/swan.png
unifetch/crests/tees.png
unifetch/crests/ucl.png
unifetch/crests/uea.png
unifetch/crests/uwe.png
unifetch/crests/warwick.png
unifetch/crests/york.png
unifetch-0.1.5.dist-info/LICENSE.md
unifetch-0.1.5.dist-info/METADATA
unifetch-0.1.5.dist-info/WHEEL
unifetch-0.1.5.dist-info/top_level.txt
unifetch-0.1.5.dist-info/RECORD
