Metadata-Version: 2.1
Name: unifetch
Version: 0.1.5
Summary: Unifetch is a python script that will display the logo and motto of a UK university
Home-page: https://github.com/LukeBriggsDev/unifetch
Author: Luke Briggs
Author-email: contact@lukebriggs.dev
License: UNKNOWN
Platform: UNKNOWN
Classifier: Programming Language :: Python :: 3
Classifier: License :: OSI Approved :: MIT License
Classifier: Operating System :: OS Independent
License-File: LICENSE.md
Requires-Dist: numpy
Requires-Dist: opencv-python
Requires-Dist: Pillow
